CHANGES.txt
README.txt
setup.py
Products/__init__.py
Products.ATExtensions.egg-info/PKG-INFO
Products.ATExtensions.egg-info/SOURCES.txt
Products.ATExtensions.egg-info/dependency_links.txt
Products.ATExtensions.egg-info/namespace_packages.txt
Products.ATExtensions.egg-info/not-zip-safe
Products.ATExtensions.egg-info/requires.txt
Products.ATExtensions.egg-info/top_level.txt
Products/ATExtensions/__init__.py
Products/ATExtensions/ateapi.py
Products/ATExtensions/config.py
Products/ATExtensions/configure.zcml
Products/ATExtensions/setuphandlers.py
Products/ATExtensions/Extensions/__init__.py
Products/ATExtensions/Extensions/plone2Install.py
Products/ATExtensions/Extensions/utils.py
Products/ATExtensions/datatype/__init__.py
Products/ATExtensions/datatype/formattablename.py
Products/ATExtensions/datatype/formattablenames.py
Products/ATExtensions/examples/__init__.py
Products/ATExtensions/examples/demo.py
Products/ATExtensions/examples/formattablename.py
Products/ATExtensions/field/__init__.py
Products/ATExtensions/field/comment.py
Products/ATExtensions/field/datetime.py
Products/ATExtensions/field/email.py
Products/ATExtensions/field/formattablename.py
Products/ATExtensions/field/formattablenames.py
Products/ATExtensions/field/record.py
Products/ATExtensions/field/record_examples.py
Products/ATExtensions/field/records.py
Products/ATExtensions/field/records_examples.py
Products/ATExtensions/field/remotetext.py
Products/ATExtensions/field/smartemail.py
Products/ATExtensions/field/url.py
Products/ATExtensions/i18n/i18nCall.sh
Products/ATExtensions/i18n/plone-da.po
Products/ATExtensions/i18n/plone-de.po
Products/ATExtensions/i18n/plone-en.po
Products/ATExtensions/i18n/plone-es.po
Products/ATExtensions/i18n/plone-fr.po
Products/ATExtensions/i18n/plone-generated.pot
Products/ATExtensions/i18n/plone-it.po
Products/ATExtensions/i18n/plone-manual.pot
Products/ATExtensions/i18n/plone-nl.po
Products/ATExtensions/i18n/plone-pt.po
Products/ATExtensions/profiles/default/import_steps.xml
Products/ATExtensions/profiles/default/metadata.xml
Products/ATExtensions/profiles/default/propertiestool.xml
Products/ATExtensions/profiles/default/skins.xml
Products/ATExtensions/profiles/demotypes/types.xml
Products/ATExtensions/profiles/demotypes/types/FormattableNameDemo.xml
