Metadata-Version: 1.0
Name: Products.ATExtensions
Version: 1.0
Summary: This package provides some further fields and widgets for archetypes.
Home-page: http://pypi.python.org/pypi/Products.ATExtensions
Author: Raphael Ritz
Author-email: r.ritz@biologie.hu-berlin.de
License: BSD
Platform: UNKNOWN
Classifier: Framework :: Plone
Classifier: Programming Language :: Python
